LICENSE
README.md
setup.py
min_tbox/__init__.py
min_tbox/api.py
min_tbox/cache_tools.py
min_tbox/camel_tool.py
min_tbox/tools.py
min_tbox.egg-info/PKG-INFO
min_tbox.egg-info/SOURCES.txt
min_tbox.egg-info/dependency_links.txt
min_tbox.egg-info/requires.txt
min_tbox.egg-info/top_level.txt
tests/__init__.py
tests/test_api.py
tests/test_cache_tools.py
tests/test_tools.py