Metadata-Version: 2.1
Name: min-tbox
Version: 0.0.3
Summary: some kit tool 
Author: noaghzil
Author-email: noaghzil@gmail.com
License-File: LICENSE
